impyrialTest/__init__.py
impyrialTest/utils.py
impyrialTest/length/__init__.py
impyrialTest/length/api.py
impyrialTest/length/core.py
impyrialTest/weight/__init__.py
impyrialTest/weight/api.py
impyrialTest/weight/core.py
impyrialTest-0.1.5.dist-info/LICENSE
impyrialTest-0.1.5.dist-info/METADATA
impyrialTest-0.1.5.dist-info/WHEEL
impyrialTest-0.1.5.dist-info/top_level.txt
impyrialTest-0.1.5.dist-info/RECORD
