Metadata-Version: 2.1
Name: impyrialTest
Version: 0.1.5
Summary: A package for converting imperial lengths and weights.
Author: Ahmed Elkhodary
License: MIT license
Keywords: impyrialTest
Classifier: Development Status :: 2 - Pre-Alpha
Classifier: Intended Audience :: Developers
Classifier: License :: OSI Approved :: MIT License
Classifier: Natural Language :: English
Classifier: Programming Language :: Python :: 3
Classifier: Programming Language :: Python :: 3.6
Classifier: Programming Language :: Python :: 3.8
Requires-Python: ==3.8.*
License-File: LICENSE
Requires-Dist: numpy >=1.10
Requires-Dist: pandas >=1.0.0
